reviewcheck/__init__.py
reviewcheck/__main__.py
reviewcheck/app.py
reviewcheck/cli.py
reviewcheck/config.py
reviewcheck/constants.py
reviewcheck/exceptions.py
reviewcheck/merge_request.py
reviewcheck/rich_components.py
reviewcheck/utils.py
reviewcheck-0.7.0.dist-info/LICENSE
reviewcheck-0.7.0.dist-info/METADATA
reviewcheck-0.7.0.dist-info/WHEEL
reviewcheck-0.7.0.dist-info/entry_points.txt
reviewcheck-0.7.0.dist-info/RECORD
