Metadata-Version: 2.1
Name: reviewcheck
Version: 0.7.0
Summary: Tool to stay up to date with your reviews on GitLab – Don't let a comment slip you by
Home-page: https://github.com/volvo-cars/Reviewcheck
License: Apache-2.0 license
Keywords: code review,gitlab
Author: Simon Bengtsson
Author-email: simon.bengtsson.3@volvocars.com
Requires-Python: >=3.8.1
Classifier: License :: Other/Proprietary License
Classifier: Programming Language :: Python :: 3
Classifier: Programming Language :: Python :: 3.9
Classifier: Programming Language :: Python :: 3.10
Classifier: Programming Language :: Python :: 3.11
Classifier: Programming Language :: Python :: 3.12
Requires-Dist: colorama (>=0.4.4)
Requires-Dist: pyyaml (>=5.1)
Requires-Dist: requests (>=2.27.1)
Requires-Dist: rich (>=12.4.4)
Requires-Dist: shtab (>=1.5.4)
